{".class": "MypyFile", "_fullname": "maradmin_scrapy_project.maradmin_scrapy_project.apps", "is_partial_stub_package": false, "is_stub": false, "names": {".class": "SymbolTable", "AppConfig": {".class": "SymbolTableNode", "cross_ref": "django.apps.config.AppConfig", "kind": "Gdef", "module_hidden": true, "module_public": false}, "MaradminScrapyProjectConfig": {".class": "SymbolTableNode", "kind": "Gdef", "node": {".class": "TypeInfo", "_promote": null, "abstract_attributes": [], "bases": ["django.apps.config.AppConfig"], "declared_metaclass": null, "defn": {".class": "ClassDef", "fullname": "maradmin_scrapy_project.maradmin_scrapy_project.apps.MaradminScrapyProjectConfig", "name": "MaradminScrapyProjectConfig", "type_vars": []}, "flags": [], "fullname": "maradmin_scrapy_project.maradmin_scrapy_project.apps.MaradminScrapyProjectConfig", "metaclass_type": null, "metadata": {}, "module_name": "maradmin_scrapy_project.maradmin_scrapy_project.apps", "mro": ["maradmin_scrapy_project.maradmin_scrapy_project.apps.MaradminScrapyProjectConfig", "django.apps.config.AppConfig", "builtins.object"], "names": {".class": "SymbolTable", "name": {".class": "SymbolTableNode", "kind": "Mdef", "node": {".class": "Var", "flags": ["is_initialized_in_class", "is_ready"], "fullname": "maradmin_scrapy_project.maradmin_scrapy_project.apps.MaradminScrapyProjectConfig.name", "name": "name", "type": "builtins.str"}}}, "tuple_type": null, "type_vars": [], "typeddict_type": null}}, "__doc__": {".class": "SymbolTableNode", "kind": "Gdef", "node": {".class": "Var", "flags": ["is_ready"], "fullname": "maradmin_scrapy_project.maradmin_scrapy_project.apps.__doc__", "name": "__doc__", "type": "builtins.str"}}, "__file__": {".class": "SymbolTableNode", "kind": "Gdef", "node": {".class": "Var", "flags": ["is_ready"], "fullname": "maradmin_scrapy_project.maradmin_scrapy_project.apps.__file__", "name": "__file__", "type": "builtins.str"}}, "__name__": {".class": "SymbolTableNode", "kind": "Gdef", "node": {".class": "Var", "flags": ["is_ready"], "fullname": "maradmin_scrapy_project.maradmin_scrapy_project.apps.__name__", "name": "__name__", "type": "builtins.str"}}, "__package__": {".class": "SymbolTableNode", "kind": "Gdef", "node": {".class": "Var", "flags": ["is_ready"], "fullname": "maradmin_scrapy_project.maradmin_scrapy_project.apps.__package__", "name": "__package__", "type": "builtins.str"}}}, "path": "maradmin_scrapy_project/maradmin_scrapy_project/apps.py"}