{"data_mtime": 1589985826, "dep_lines": [1, 1, 1, 1, 2], "dep_prios": [10, 5, 30, 30, 5], "dependencies": ["os", "builtins", "abc", "typing"], "hash": "9751a859d23dedda6abfd80cee6c93b9e1cb5c52c2941ac04731b5471b91a3b9", "id": "backend.celery", "ignore_all": false, "interface_hash": "2d9abd734e4cef3ea7e8312a7e98b0066b8e589db7771e7aca831927514f3d5b", "mtime": 1589985401, "options": {"allow_redefinition": false, "allow_untyped_globals": false, "always_false": [], "always_true": [], "bazel": false, "check_untyped_defs": true, "disallow_any_decorated": false, "disallow_any_explicit": false, "disallow_any_expr": false, "disallow_any_generics": true, "disallow_any_unimported": false, "disallow_incomplete_defs": false, "disallow_subclassing_any": false, "disallow_untyped_calls": true, "disallow_untyped_decorators": false, "disallow_untyped_defs": true, "follow_imports": "normal", "follow_imports_for_stubs": false, "ignore_errors": false, "ignore_missing_imports": true, "implicit_reexport": false, "local_partial_types": false, "mypyc": false, "no_implicit_optional": true, "platform": "darwin", "plugins": ["mypy_django_plugin.main", "mypy_drf_plugin.main"], "show_none_errors": true, "strict_equality": true, "strict_optional": true, "strict_optional_whitelist": null, "warn_no_return": false, "warn_return_any": true, "warn_unreachable": true, "warn_unused_ignores": true}, "path": "backend/celery.py", "plugin_data": null, "size": 251, "suppressed": ["celery"], "version_id": "0.770"}